hydra_plugins/dashit/__init__.py
hydra_plugins/dashit/config.py
hydra_plugins/dashit/constants.py
hydra_plugins/dashit/launcher.py
hydra_plugins/dashit/status.py
hydra_plugins/dashit/utils.py
dashit-1.2.0.dist-info/METADATA
dashit-1.2.0.dist-info/WHEEL
dashit-1.2.0.dist-info/top_level.txt
dashit-1.2.0.dist-info/RECORD
