Metadata-Version: 2.1
Name: dashit
Version: 1.2.0
Summary: Custom Command Submitit Launcher for Hydra apps
Home-page: https://github.com/sede-x/dashit
Author: Adhitya
Author-email: a.kamakshidasan@shell.com
License: UNKNOWN
Platform: UNKNOWN
Classifier: License :: OSI Approved :: MIT License
Classifier: Programming Language :: Python :: 3.7
Classifier: Programming Language :: Python :: 3.8
Classifier: Programming Language :: Python :: 3.9
Classifier: Programming Language :: Python :: 3.10
Classifier: Programming Language :: Python :: 3.11
Classifier: Operating System :: MacOS
Classifier: Operating System :: POSIX :: Linux
Classifier: Development Status :: 4 - Beta
Requires-Dist: hydra-core (>=1.3.2)
Requires-Dist: submitit (>=1.5.1)
